excel_models/__init__.py
excel_models/db.py
excel_models/exceptions.py
excel_models/typing.py
excel_models/column_inst/__init__.py
excel_models/column_inst/_base.py
excel_models/column_inst/_std.py
excel_models/column_inst/array.py
excel_models/column_inst/map.py
excel_models/column_inst/remainder.py
excel_models/columns/__init__.py
excel_models/columns/_base.py
excel_models/columns/_container.py
excel_models/columns/_std.py
excel_models/columns/basic_types.py
excel_models/columns/collection_types.py
excel_models/columns/datetime.py
excel_models/columns/multi.py
excel_models/models/__init__.py
excel_models/models/_base.py
excel_models/models/_std.py
excel_models/tables/__init__.py
excel_models/tables/_base.py
excel_models/tables/_inst.py
excel_models/tables/_std.py
excel_models/utils/__init__.py
excel_models/utils/assignable_property.py
excel_models/utils/class_collector.py
excel_models/utils/collections.py
excel_models/utils/descriptors.py
excel_models/validators/__init__.py
excel_models/validators/comparisons.py
excel_models-0.3.2.dist-info/LICENSE
excel_models-0.3.2.dist-info/METADATA
excel_models-0.3.2.dist-info/WHEEL
excel_models-0.3.2.dist-info/top_level.txt
excel_models-0.3.2.dist-info/RECORD
