Metadata-Version: 2.1
Name: excel-models
Version: 0.3.2
Summary: Model-style Excel File Accessor
Home-page: https://github.com/MichaelKim0407/excel-models
Author: Zheng Jin
Author-email: mkim0407@gmail.com
License: MIT
Classifier: Intended Audience :: Developers
Classifier: Development Status :: 3 - Alpha
Classifier: License :: OSI Approved :: MIT License
Classifier: Programming Language :: Python
Classifier: Programming Language :: Python :: 3
Classifier: Programming Language :: Python :: 3.11
Classifier: Topic :: Software Development :: Libraries :: Python Modules
Requires-Python: >=3.11
License-File: LICENSE
Requires-Dist: openpyxl
Requires-Dist: returns-decorator
Provides-Extra: ci
Requires-Dist: flake8 ; extra == 'ci'
Requires-Dist: flake8-commas ; extra == 'ci'
Requires-Dist: flake8-quotes ; extra == 'ci'
Requires-Dist: pytest ; extra == 'ci'
Requires-Dist: pytest-cov ; extra == 'ci'
Requires-Dist: coveralls ; extra == 'ci'
Provides-Extra: dev
Requires-Dist: flake8 ; extra == 'dev'
Requires-Dist: flake8-commas ; extra == 'dev'
Requires-Dist: flake8-quotes ; extra == 'dev'
Requires-Dist: pytest ; extra == 'dev'
Requires-Dist: pytest-cov ; extra == 'dev'
